coremlprofiler/__init__.py
coremlprofiler/cli.py
coremlprofiler/prof.py
coremlprofiler-0.4.0.dist-info/METADATA
coremlprofiler-0.4.0.dist-info/WHEEL
coremlprofiler-0.4.0.dist-info/entry_points.txt
coremlprofiler-0.4.0.dist-info/RECORD
